findfour/__init__.py
findfour-0.0.1.dist-info/METADATA
findfour-0.0.1.dist-info/WHEEL
findfour-0.0.1.dist-info/licenses/LICENSE
findfour-0.0.1.dist-info/RECORD
