Metadata-Version: 2.3
Name: findfour
Version: 0.0.1
Summary: SOME DESCRIPTION
Project-URL: Homepage, https://github.com/zlliu246/findfour
Project-URL: Issues, https://github.com/zlliu246/findfour/issues
Author-email: Liu Zuo Lin <zlliu246@gmail.com>
Classifier: License :: OSI Approved :: MIT License
Classifier: Operating System :: OS Independent
Classifier: Programming Language :: Python :: 3
Requires-Python: >=3.8
